{
	"info": {
		"_postman_id": "ff372ed6-e5d9-4ead-adf7-467607fa1b1b",
		"name": "bizket_assessment",
		"schema": "https://schema.getpostman.com/json/collection/v2.1.0/collection.json"
	},
	"item": [
		{
			"name": "v1",
			"item": [
				{
					"name": "playground",
					"item": [
						{
							"name": "users",
							"request": {
								"method": "GET",
								"header": [],
								"url": {
									"raw": "http://127.0.0.1:5000/users",
									"protocol": "http",
									"host": [
										"127",
										"0",
										"0",
										"1"
									],
									"port": "5000",
									"path": [
										"users"
									]
								}
							},
							"response": []
						},
						{
							"name": "users",
							"request": {
								"method": "POST",
								"header": [],
								"body": {
									"mode": "raw",
									"raw": "{\r\n    \"name\"          :   \"Rhuver Pedere\",\r\n    \"age\"           :   26,\r\n    \"occupation\"    :   \"Software Developer\"  \r\n}",
									"options": {
										"raw": {
											"language": "json"
										}
									}
								},
								"url": {
									"raw": "http://127.0.0.1:5000/users",
									"protocol": "http",
									"host": [
										"127",
										"0",
										"0",
										"1"
									],
									"port": "5000",
									"path": [
										"users"
									]
								}
							},
							"response": []
						},
						{
							"name": "users/:id",
							"request": {
								"method": "GET",
								"header": [],
								"url": {
									"raw": "http://127.0.0.1:5000/users/:id",
									"protocol": "http",
									"host": [
										"127",
										"0",
										"0",
										"1"
									],
									"port": "5000",
									"path": [
										"users",
										":id"
									],
									"variable": [
										{
											"key": "id",
											"value": "7"
										}
									]
								}
							},
							"response": []
						},
						{
							"name": "users/:id",
							"request": {
								"method": "PUT",
								"header": [],
								"body": {
									"mode": "raw",
									"raw": "{\r\n    \"occupation\"          :   \"Programmer\"\r\n}",
									"options": {
										"raw": {
											"language": "json"
										}
									}
								},
								"url": {
									"raw": "http://127.0.0.1:5000/users/:id",
									"protocol": "http",
									"host": [
										"127",
										"0",
										"0",
										"1"
									],
									"port": "5000",
									"path": [
										"users",
										":id"
									],
									"variable": [
										{
											"key": "id",
											"value": "7"
										}
									]
								}
							},
							"response": []
						},
						{
							"name": "users/:id",
							"request": {
								"method": "DELETE",
								"header": [],
								"url": {
									"raw": "http://127.0.0.1:5000/users/:id",
									"protocol": "http",
									"host": [
										"127",
										"0",
										"0",
										"1"
									],
									"port": "5000",
									"path": [
										"users",
										":id"
									],
									"variable": [
										{
											"key": "id",
											"value": "7"
										}
									]
								}
							},
							"response": []
						}
					]
				},
				{
					"name": "match",
					"request": {
						"method": "GET",
						"header": [],
						"url": {
							"raw": "http://127.0.0.1:5000/match/:match_id",
							"protocol": "http",
							"host": [
								"127",
								"0",
								"0",
								"1"
							],
							"port": "5000",
							"path": [
								"match",
								":match_id"
							],
							"variable": [
								{
									"key": "match_id",
									"value": "8"
								}
							]
						}
					},
					"response": []
				},
				{
					"name": "search",
					"request": {
						"method": "GET",
						"header": [],
						"url": {
							"raw": "http://127.0.0.1:5000/search?id=5&name=Joe&age=30&occupation=Arc",
							"protocol": "http",
							"host": [
								"127",
								"0",
								"0",
								"1"
							],
							"port": "5000",
							"path": [
								"search"
							],
							"query": [
								{
									"key": "id",
									"value": "5"
								},
								{
									"key": "name",
									"value": "Joe"
								},
								{
									"key": "age",
									"value": "30"
								},
								{
									"key": "occupation",
									"value": "Arc"
								}
							]
						}
					},
					"response": []
				}
			]
		},
		{
			"name": "v2",
			"item": [
				{
					"name": "playgroundV2",
					"item": [
						{
							"name": "users",
							"item": [
								{
									"name": "users",
									"request": {
										"method": "GET",
										"header": [],
										"url": {
											"raw": "http://127.0.0.1:5000/v2/users",
											"protocol": "http",
											"host": [
												"127",
												"0",
												"0",
												"1"
											],
											"port": "5000",
											"path": [
												"v2",
												"users"
											]
										}
									},
									"response": []
								},
								{
									"name": "users",
									"request": {
										"method": "POST",
										"header": [],
										"body": {
											"mode": "raw",
											"raw": "{\r\n    \"name\"          :   \"RJ Pedere\",\r\n    \"age\"           :   26,\r\n    \"occupation\"    :   \"Software Developer\"  \r\n}",
											"options": {
												"raw": {
													"language": "json"
												}
											}
										},
										"url": {
											"raw": "http://127.0.0.1:5000/v2/users",
											"protocol": "http",
											"host": [
												"127",
												"0",
												"0",
												"1"
											],
											"port": "5000",
											"path": [
												"v2",
												"users"
											]
										}
									},
									"response": []
								},
								{
									"name": "users/:id",
									"request": {
										"method": "GET",
										"header": [],
										"url": {
											"raw": "http://127.0.0.1:5000/v2/users/:id",
											"protocol": "http",
											"host": [
												"127",
												"0",
												"0",
												"1"
											],
											"port": "5000",
											"path": [
												"v2",
												"users",
												":id"
											],
											"variable": [
												{
													"key": "id",
													"value": "12"
												}
											]
										}
									},
									"response": []
								},
								{
									"name": "users/:id",
									"request": {
										"method": "PUT",
										"header": [],
										"body": {
											"mode": "raw",
											"raw": "{\r\n    \"age\":19\r\n}",
											"options": {
												"raw": {
													"language": "json"
												}
											}
										},
										"url": {
											"raw": "http://127.0.0.1:5000/v2/users/:id",
											"protocol": "http",
											"host": [
												"127",
												"0",
												"0",
												"1"
											],
											"port": "5000",
											"path": [
												"v2",
												"users",
												":id"
											],
											"variable": [
												{
													"key": "id",
													"value": "14"
												}
											]
										}
									},
									"response": []
								},
								{
									"name": "users/:id",
									"request": {
										"method": "DELETE",
										"header": [],
										"url": {
											"raw": "http://127.0.0.1:5000/v2/users/:id",
											"protocol": "http",
											"host": [
												"127",
												"0",
												"0",
												"1"
											],
											"port": "5000",
											"path": [
												"v2",
												"users",
												":id"
											],
											"variable": [
												{
													"key": "id",
													"value": "11"
												}
											]
										}
									},
									"response": []
								}
							]
						},
						{
							"name": "interests",
							"item": [
								{
									"name": "FavNums",
									"request": {
										"method": "GET",
										"header": [],
										"url": {
											"raw": "http://127.0.0.1:5000/v2/interests/:user_id",
											"protocol": "http",
											"host": [
												"127",
												"0",
												"0",
												"1"
											],
											"port": "5000",
											"path": [
												"v2",
												"interests",
												":user_id"
											],
											"variable": [
												{
													"key": "user_id",
													"value": "12"
												}
											]
										}
									},
									"response": []
								},
								{
									"name": "FavNums",
									"request": {
										"method": "POST",
										"header": [],
										"body": {
											"mode": "raw",
											"raw": "{\r\n    \"favnums\" : [\r\n        21, 22, 23, 34\r\n    ]\r\n}",
											"options": {
												"raw": {
													"language": "json"
												}
											}
										},
										"url": {
											"raw": "http://127.0.0.1:5000/v2/interests/:user_id",
											"protocol": "http",
											"host": [
												"127",
												"0",
												"0",
												"1"
											],
											"port": "5000",
											"path": [
												"v2",
												"interests",
												":user_id"
											],
											"variable": [
												{
													"key": "user_id",
													"value": "4"
												}
											]
										}
									},
									"response": []
								},
								{
									"name": "matchV2",
									"request": {
										"method": "GET",
										"header": [],
										"url": {
											"raw": "http://127.0.0.1:5000/v2/interests/:user_id/match/:match_id",
											"protocol": "http",
											"host": [
												"127",
												"0",
												"0",
												"1"
											],
											"port": "5000",
											"path": [
												"v2",
												"interests",
												":user_id",
												"match",
												":match_id"
											],
											"variable": [
												{
													"key": "user_id",
													"value": "3"
												},
												{
													"key": "match_id",
													"value": "2"
												}
											]
										}
									},
									"response": []
								}
							]
						}
					]
				},
				{
					"name": "searchV2",
					"request": {
						"method": "GET",
						"header": [],
						"url": {
							"raw": "http://127.0.0.1:5000/v2/search?id=5&age=30",
							"protocol": "http",
							"host": [
								"127",
								"0",
								"0",
								"1"
							],
							"port": "5000",
							"path": [
								"v2",
								"search"
							],
							"query": [
								{
									"key": "id",
									"value": "5"
								},
								{
									"key": "name",
									"value": "Jo",
									"disabled": true
								},
								{
									"key": "age",
									"value": "30"
								},
								{
									"key": "occupation",
									"value": "er",
									"disabled": true
								}
							]
						}
					},
					"response": []
				}
			]
		},
		{
			"name": "HelloWorld!",
			"request": {
				"method": "GET",
				"header": [],
				"url": {
					"raw": "http://127.0.0.1:5000/",
					"protocol": "http",
					"host": [
						"127",
						"0",
						"0",
						"1"
					],
					"port": "5000",
					"path": [
						""
					]
				}
			},
			"response": []
		}
	]
}